LICENSE
src/__init__.py
src/checker.py
flake8_zale-0.2.1.dist-info/LICENSE
flake8_zale-0.2.1.dist-info/METADATA
flake8_zale-0.2.1.dist-info/WHEEL
flake8_zale-0.2.1.dist-info/entry_points.txt
flake8_zale-0.2.1.dist-info/RECORD
