Metadata-Version: 2.1
Name: flake8-zale
Version: 0.2.1
Summary: Indentation checker for flake8
Home-page: https://github.com/Kirill-Lekhov/flake8-zale
License: MIT
Keywords: flake8,plugin
Author: Kirill_Lekhov
Author-email: Kirill.Lekhov@mail.ru
Requires-Python: >=3.8.1,<4.0.0
Classifier: License :: OSI Approved :: MIT License
Classifier: Programming Language :: Python :: 3
Classifier: Programming Language :: Python :: 3.9
Classifier: Programming Language :: Python :: 3.10
Classifier: Programming Language :: Python :: 3.11
Classifier: Programming Language :: Python :: 3.12
Project-URL: Repository, https://github.com/Kirill-Lekhov/flake8-zale
